orio/__init__.py
orio/main/__init__.py
orio/main/ann_gen.py
orio/main/ann_parser.py
orio/main/cmd_line_opts.py
orio/main/code_frag.py
orio/main/dyn_loader.py
orio/main/opt_driver.py
orio/main/orio_main.py
orio/main/pragma_preprocessor.py
orio/main/st_builder.py
orio/main/tuning_spec_template.py
orio/main/parsers/__init__.py
orio/main/parsers/ast.py
orio/main/parsers/fAST.py
orio/main/parsers/fcodegen.py
orio/main/parsers/flexer.py
orio/main/parsers/fparser.py
orio/main/parsers/oldAST.py
orio/main/parsers/plyparser.py
orio/main/parsers/sublexer.py
orio/main/parsers/pycparser/__init__.py
orio/main/parsers/pycparser/_ast_gen.py
orio/main/parsers/pycparser/_build_tables.py
orio/main/parsers/pycparser/c_ast.py
orio/main/parsers/pycparser/c_lexer.py
orio/main/parsers/pycparser/c_parser.py
orio/main/parsers/pycparser/lextab.py
orio/main/parsers/pycparser/plyparser.py
orio/main/parsers/pycparser/yacctab.py
orio/main/tspec/__init__.py
orio/main/tspec/eval.py
orio/main/tspec/parser.py
orio/main/tspec/pparser.py
orio/main/tspec/tspec.py
orio/main/tspec/tune_info.py
orio/main/tuner/__init__.py
orio/main/tuner/ptest_codegen.py
orio/main/tuner/ptest_driver.py
orio/main/tuner/skeleton_code.py
orio/main/tuner/stats.py
orio/main/tuner/tuner.py
orio/main/tuner/search/__init__.py
orio/main/tuner/search/search.py
orio/main/tuner/search/z3_search.py
orio/main/tuner/search/annealing/__init__.py
orio/main/tuner/search/annealing/annealing.py
orio/main/tuner/search/cudacfg/__init__.py
orio/main/tuner/search/cudacfg/cudacfg.py
orio/main/tuner/search/direct/__init__.py
orio/main/tuner/search/direct/direct.py
orio/main/tuner/search/exhaustive/__init__.py
orio/main/tuner/search/exhaustive/exhaustive.py
orio/main/tuner/search/extern/__init__.py
orio/main/tuner/search/extern/extern.py
orio/main/tuner/search/firefly/__init__.py
orio/main/tuner/search/firefly/firefly.py
orio/main/tuner/search/firefly/firefly_old.py
orio/main/tuner/search/firefly/firefly_prez3.py
orio-0.6.1.dist-info/LICENSE
orio-0.6.1.dist-info/METADATA
orio-0.6.1.dist-info/WHEEL
orio-0.6.1.dist-info/top_level.txt
orio-0.6.1.dist-info/RECORD
