Metadata-Version: 2.1
Name: orio
Version: 0.6.1
Summary: ORIO -- An Annotation-Based Performance Tuning Tool
Home-page: https://github.com/brnorris03/Orio
Author: Boyana Norris and Albert Hartono
Author-email: brnorris03@gmail.com
Maintainer: Boyana Norris
Maintainer-email: brnorris03@gmail.com
License: UNKNOWN
Platform: UNKNOWN
Classifier: Programming Language :: Python :: 3
Classifier: License :: OSI Approved :: MIT License
Classifier: Operating System :: OS Independent
Requires-Python: >=3.6
